euporie/console/__init__.py
euporie/console/__main__.py
euporie/console/_commands.py
euporie/console/_settings.py
euporie/console/app.py
euporie/console/py.typed
euporie/console/tabs/__init__.py
euporie/console/tabs/console.py
euporie/core/__init__.py
euporie/core/__main__.py
euporie/core/_settings.py
euporie/core/async_utils.py
euporie/core/border.py
euporie/core/cache.py
euporie/core/clipboard.py
euporie/core/commands.py
euporie/core/completion.py
euporie/core/config.py
euporie/core/data_structures.py
euporie/core/diagnostics.py
euporie/core/filters.py
euporie/core/format.py
euporie/core/fsspec.py
euporie/core/graphics.py
euporie/core/history.py
euporie/core/inspection.py
euporie/core/io.py
euporie/core/keys.py
euporie/core/lexers.py
euporie/core/log.py
euporie/core/lsp.py
euporie/core/margins.py
euporie/core/mouse_events.py
euporie/core/nbformat.py
euporie/core/path.py
euporie/core/processors.py
euporie/core/py.typed
euporie/core/pygments.py
euporie/core/reference.py
euporie/core/renderer.py
euporie/core/style.py
euporie/core/suggest.py
euporie/core/utils.py
euporie/core/validation.py
euporie/core/app/__init__.py
euporie/core/app/_commands.py
euporie/core/app/_settings.py
euporie/core/app/app.py
euporie/core/app/base.py
euporie/core/app/current.py
euporie/core/app/cursor.py
euporie/core/app/dummy.py
euporie/core/app/launch.py
euporie/core/bars/__init__.py
euporie/core/bars/command.py
euporie/core/bars/menu.py
euporie/core/bars/search.py
euporie/core/bars/status.py
euporie/core/comm/__init__.py
euporie/core/comm/base.py
euporie/core/comm/ipympl.py
euporie/core/comm/ipywidgets.py
euporie/core/comm/registry.py
euporie/core/convert/__init__.py
euporie/core/convert/datum.py
euporie/core/convert/mime.py
euporie/core/convert/registry.py
euporie/core/convert/utils.py
euporie/core/convert/formats/__init__.py
euporie/core/convert/formats/ansi.py
euporie/core/convert/formats/base64.py
euporie/core/convert/formats/common.py
euporie/core/convert/formats/ft.py
euporie-2.10.3.dist-info/METADATA
euporie-2.10.3.dist-info/WHEEL
euporie-2.10.3.dist-info/entry_points.txt
euporie-2.10.3.dist-info/licenses/LICENSE
euporie-2.10.3.dist-info/RECORD
