Metadata-Version: 2.4
Name: euporie
Version: 2.10.3
Summary: Euporie is a suite of terminal applications for interacting with Jupyter kernels
Project-URL: Documentation, https://euporie.readthedocs.io/en/latest
Project-URL: Issues, https://github.com/joouha/euporie/issues
Project-URL: Source, https://github.com/joouha/euporie
Project-URL: Changelog, https://euporie.readthedocs.io/en/latest/pages/changelog.html
Author-email: Josiah Outram Halstead <josiah@halstead.email>
License-File: LICENSE
Keywords: euporie,ipython,jupyter,markdown,notebook,terminal
Classifier: Development Status :: 4 - Beta
Classifier: Environment :: Console
Classifier: Framework :: Jupyter
Classifier: Programming Language :: Python
Classifier: Programming Language :: Python :: 3.10
Classifier: Programming Language :: Python :: 3.11
Classifier: Programming Language :: Python :: 3.12
Classifier: Programming Language :: Python :: 3.13
Classifier: Programming Language :: Python :: 3.14
Classifier: Programming Language :: Python :: Implementation :: CPython
Classifier: Programming Language :: Python :: Implementation :: PyPy
Classifier: Topic :: Scientific/Engineering
Requires-Python: >=3.10
Requires-Dist: fastjsonschema~=2.15
Requires-Dist: flatlatex~=0.15
Requires-Dist: fsspec[http]>=2022.12.0
Requires-Dist: imagesize~=1.3
Requires-Dist: jupyter-client>=7.1
Requires-Dist: jupytext>=1.14.0
Requires-Dist: linkify-it-py~=2.0
Requires-Dist: markdown-it-py~=3.0
Requires-Dist: mdit-py-plugins~=0.4.2
Requires-Dist: nbformat~=5.0
Requires-Dist: pillow>=9.0
Requires-Dist: platformdirs~=3.5
Requires-Dist: prompt-toolkit>=3.0.52
Requires-Dist: pygments~=2.11
Requires-Dist: pyperclip~=1.9
Requires-Dist: python-code-minimap>=0.1.1
Requires-Dist: sixelcrop~=0.1.9
Requires-Dist: timg~=1.1.6
Requires-Dist: typing-extensions~=4.5
Requires-Dist: universal-pathlib~=0.2.1
Provides-Extra: hub
Requires-Dist: asyncssh~=2.18; extra == 'hub'
